awslambdamonitor/__init__.py
awslambdamonitor/monitor.py
awslambdamonitor-1.0.0.dist-info/DESCRIPTION.rst
awslambdamonitor-1.0.0.dist-info/METADATA
awslambdamonitor-1.0.0.dist-info/RECORD
awslambdamonitor-1.0.0.dist-info/WHEEL
awslambdamonitor-1.0.0.dist-info/metadata.json
awslambdamonitor-1.0.0.dist-info/top_level.txt
