Metadata-Version: 2.0
Name: awslambdamonitor
Version: 1.0.0
Summary: A small monitoring tool which runs in AWS Lambda
Home-page: https://github.com/gene1wood/awslambdamonitor
Author: Gene Wood
Author-email: gene_wood@cementhorizon.com
License: GPL-3.0
Keywords: aws lambda monitoring ses
Platform: UNKNOWN
Classifier: Development Status :: 3 - Alpha
Classifier: Intended Audience :: System Administrators
Classifier: Topic :: System :: Monitoring
Classifier: License :: OSI Approved :: GNU General Public License v3 (GPLv3)
Classifier: Programming Language :: Python :: 2
Classifier: Programming Language :: Python :: 2.7
Requires-Dist: PyYAML
Requires-Dist: boto3
Requires-Dist: ecdsa
Requires-Dist: ndg-httpsclient
Requires-Dist: paramiko
Requires-Dist: pyOpenSSL
Requires-Dist: pyasn1
Requires-Dist: pycrypto
Requires-Dist: python-whois
Requires-Dist: requests
